pyretest/__init__.py
pyretest/pooled_kappa/__init__.py
pyretest/pooled_kappa/bootstrap.py
pyretest/pooled_kappa/pooled_cohen_kappa.py
pyretest/sampler/__init__.py
pyretest/sampler/sample_questionnaire.py
pyretest-1.3.dist-info/LICENSE
pyretest-1.3.dist-info/METADATA
pyretest-1.3.dist-info/WHEEL
pyretest-1.3.dist-info/top_level.txt
pyretest-1.3.dist-info/RECORD
