Metadata-Version: 2.1
Name: pyretest
Version: 1.3
Summary: Library to measure test-retest reliability and to estimate adequate sample size using simulated questionnaire responses.
Home-page: https://github.com/albertbuchard/pyretest
Author: Albert Buchard
Author-email: albert.buchard@gmail.com
License: MIT
Platform: UNKNOWN
Classifier: Programming Language :: Python :: 3
Classifier: License :: OSI Approved :: MIT License
Classifier: Operating System :: OS Independent
License-File: LICENSE
Requires-Dist: numpy
Requires-Dist: pandas
Requires-Dist: tqdm
